{
  "environment_check": {
    "status": "completed",
    "completed_at": "2025-09-14T13:40:15.288573",
    "validation_result": null,
    "metadata": {}
  },
  "dataset_download": {
    "status": "completed",
    "completed_at": "2025-09-14T13:40:15.828603",
    "validation_result": {
      "valid": true,
      "errors": [],
      "warnings": [],
      "stats": {
        "total_images": 1649,
        "species_counts": {
          "Falciparum": 1505,
          "Vivax": 144
        },
        "dataset_type": "classification"
      },
      "repair_needed": false
    },
    "metadata": {}
  },
  "detection_preparation": {
    "status": "completed",
    "completed_at": "2025-09-14T13:43:08.409049",
    "validation_result": {
      "valid": true,
      "errors": [],
      "warnings": [],
      "stats": {
        "total_images": 103,
        "total_labels": 103,
        "corrupt_images": 0
      },
      "repair_needed": false
    },
    "metadata": {}
  },
  "parasite_cropping": {
    "status": "completed",
    "completed_at": "2025-09-14T13:43:18.414669",
    "validation_result": {
      "valid": true,
      "errors": [],
      "warnings": [],
      "stats": {
        "train_crops": 869,
        "val_crops": 186,
        "test_crops": 187,
        "total_crops": 1242,
        "corrupt_crops": 0,
        "small_crops": 0
      },
      "repair_needed": false
    },
    "metadata": {}
  },
  "training_system_test": {
    "status": "completed",
    "completed_at": "2025-09-14T13:44:56.667883",
    "validation_result": null,
    "metadata": {}
  }
}